amazon_affiliate_url/__init__.py
amazon_affiliate_url/amazon_affiliate_url.py
amazon_affiliate_url/country.py
amazon_affiliate_url-0.1.4.dist-info/LICENSE
amazon_affiliate_url-0.1.4.dist-info/METADATA
amazon_affiliate_url-0.1.4.dist-info/WHEEL
amazon_affiliate_url-0.1.4.dist-info/top_level.txt
amazon_affiliate_url-0.1.4.dist-info/RECORD
