Metadata-Version: 2.1
Name: amazon-affiliate-url
Version: 0.1.4
Summary: amazon_affiliate_url
Home-page: https://github.com/kkristof200/amazon_affiliate_url
Author: Kristof
License: UNKNOWN
Platform: UNKNOWN
Classifier: Programming Language :: Python :: 3
Classifier: License :: OSI Approved :: MIT License
Classifier: Operating System :: OS Independent
Requires-Python: >=3.5
Requires-Dist: bitlyshortener
